jcc
jcc2
